dont.py
dont-0.1.0.dist-info/WHEEL
dont-0.1.0.dist-info/METADATA
dont-0.1.0.dist-info/RECORD
