Metadata-Version: 2.1
Name: dont
Version: 0.1.0
Summary: Context manager base class that allows customizing execution of the contents
Author: L3viathan
Author-email: git@l3vi.de
Requires-Python: >=3.8,<4.0
Classifier: Programming Language :: Python :: 3
Classifier: Programming Language :: Python :: 3.10
Classifier: Programming Language :: Python :: 3.8
Classifier: Programming Language :: Python :: 3.9
